proofreader/__init__.py
proofreader/main.py
proofreader/core/__init__.py
proofreader/core/config.py
proofreader/core/detector.py
proofreader/core/matcher.py
proofreader/core/ocr.py
proofreader/core/resolver.py
proofreader/core/schema.py
proofreader/train/builder.py
proofreader/train/train.py
proofreader/train/emulator/generator.py
rbx_proofreader-1.0.0.dist-info/licenses/LICENSE
rbx_proofreader-1.0.0.dist-info/METADATA
rbx_proofreader-1.0.0.dist-info/WHEEL
rbx_proofreader-1.0.0.dist-info/top_level.txt
rbx_proofreader-1.0.0.dist-info/RECORD
