Metadata-Version: 2.4
Name: rbx-proofreader
Version: 1.0.0
Summary: Visual trade detection and OCR engine
License: MIT
Requires-Python: >=3.12
License-File: LICENSE
Requires-Dist: easyocr>=1.7.0
Requires-Dist: numpy>=1.24.0
Requires-Dist: opencv-python>=4.8.0
Requires-Dist: Pillow>=10.0.0
Requires-Dist: playwright>=1.40.0
Requires-Dist: rapidfuzz>=3.0.0
Requires-Dist: requests>=2.31.0
Requires-Dist: torch>=2.0.0
Requires-Dist: tqdm>=4.66.0
Requires-Dist: transformers>=4.30.0
Requires-Dist: ultralytics>=8.0.0
Dynamic: license-file
